rohkun-3.3.3.4.dist-info/licenses/LICENSE
rohkun_cli/__init__.py
rohkun_cli/auth.py
rohkun_cli/config.py
rohkun_cli/core.py
rohkun_cli/frontend_inspector.py
rohkun_cli/main.py
rohkun_cli/analyzer/__init__.py
rohkun_cli/analyzer/api_calls.py
rohkun_cli/analyzer/blast_radius.py
rohkun_cli/analyzer/confidence.py
rohkun_cli/analyzer/dependencies.py
rohkun_cli/analyzer/endpoints.py
rohkun_cli/analyzer/matcher.py
rohkun_cli/analyzer/scanner.py
rohkun_cli/knowledge_graph/__init__.py
rohkun_cli/knowledge_graph/api.py
rohkun_cli/knowledge_graph/html_generator.py
rohkun_cli/knowledge_graph/server.py
rohkun_cli/knowledge_graph/ui_server.py
rohkun_cli/knowledge_graph/designer_handoff/JSON_SCHEMA.md
rohkun_cli/knowledge_graph/designer_handoff/README.md
rohkun_cli/knowledge_graph/designer_handoff/example-data.json
rohkun_cli/knowledge_graph/designer_handoff/index.html
rohkun_cli/knowledge_graph/designer_handoff/script.js
rohkun_cli/knowledge_graph/designer_handoff/styles.css
rohkun_cli/knowledge_graph/documentation/README.md
rohkun_cli/knowledge_graph/documentation/html2canvas-configuration.md
rohkun_cli/knowledge_graph/documentation/html2canvas-documentation.md
rohkun_cli/knowledge_graph/documentation/html2canvas-faq.md
rohkun_cli/knowledge_graph/documentation/html2canvas-features.md
rohkun_cli/knowledge_graph/documentation/html2canvas-getting-started.md
rohkun_cli/knowledge_graph/documentation/html2canvas-proxy.md
rohkun_cli/knowledge_graph/documentation/html2canvas-readme.md
rohkun_cli/knowledge_graph/documentation/jetbrains-mono-readme.md
rohkun_cli/knowledge_graph/documentation/vis-network-configure.html
rohkun_cli/knowledge_graph/documentation/vis-network-edges.html
rohkun_cli/knowledge_graph/documentation/vis-network-interaction.html
rohkun_cli/knowledge_graph/documentation/vis-network-layout.html
rohkun_cli/knowledge_graph/documentation/vis-network-nodes.html
rohkun_cli/knowledge_graph/documentation/vis-network-physics.html
rohkun_cli/knowledge_graph/documentation/vis-network-readme.md
rohkun-3.3.3.4.dist-info/METADATA
rohkun-3.3.3.4.dist-info/WHEEL
rohkun-3.3.3.4.dist-info/entry_points.txt
rohkun-3.3.3.4.dist-info/top_level.txt
rohkun-3.3.3.4.dist-info/RECORD
