Metadata-Version: 2.4
Name: rohkun
Version: 3.3.3.4
Summary: Client-side code analysis tool for API connections
Home-page: https://rohkun.com
Author: Rohkun Labs
Author-email: Rohkun Labs <support@rohkun.com>
License: Proprietary
Project-URL: Homepage, https://rohkun.com
Project-URL: Documentation, https://docs.rohkun.com
Project-URL: Repository, https://github.com/rohkun/rohkun-cli
Project-URL: Issues, https://github.com/rohkun/rohkun-cli/issues
Keywords: code-analysis,api,static-analysis,developer-tools
Classifier: Development Status :: 4 - Beta
Classifier: Intended Audience :: Developers
Classifier: License :: Other/Proprietary License
Classifier: Programming Language :: Python :: 3
Classifier: Programming Language :: Python :: 3.8
Classifier: Programming Language :: Python :: 3.9
Classifier: Programming Language :: Python :: 3.10
Classifier: Programming Language :: Python :: 3.11
Classifier: Programming Language :: Python :: 3.12
Requires-Python: >=3.8
License-File: LICENSE
Requires-Dist: requests>=2.31.0
Requires-Dist: pyperclip>=1.8.2
Requires-Dist: tree-sitter>=0.20.0
Requires-Dist: tree-sitter-python>=0.20.0
Requires-Dist: tree-sitter-javascript>=0.20.0
Requires-Dist: tree-sitter-typescript>=0.20.0
Requires-Dist: tree-sitter-go>=0.20.0
Requires-Dist: tree-sitter-java>=0.20.0
Dynamic: author
Dynamic: home-page
Dynamic: license-file
Dynamic: requires-python
